{
  "ep_length_mean": {
    "steps": [
      25
    ],
    "timestamps": [
      "2023-07-05T15:52:39.951800"
    ],
    "values": [
      25.0
    ]
  },
  "epsilon": {
    "steps": [
      25
    ],
    "timestamps": [
      "2023-07-05T15:52:39.951839"
    ],
    "values": [
      1.0
    ]
  },
  "grad_norm": {
    "steps": [
      800
    ],
    "timestamps": [
      "2023-07-05T15:52:45.535774"
    ],
    "values": [
      2.7148139476776123
    ]
  },
  "loss": {
    "steps": [
      800
    ],
    "timestamps": [
      "2023-07-05T15:52:45.535690"
    ],
    "values": [
      1.0236855745315552
    ]
  },
  "q_taken_mean": {
    "steps": [
      800
    ],
    "timestamps": [
      "2023-07-05T15:52:45.536016"
    ],
    "values": [
      0.09590045928955078
    ]
  },
  "return_mean": {
    "steps": [
      25
    ],
    "timestamps": [
      "2023-07-05T15:52:39.951564"
    ],
    "values": [
      -751.2872118493016
    ]
  },
  "return_std": {
    "steps": [
      25
    ],
    "timestamps": [
      "2023-07-05T15:52:39.951755"
    ],
    "values": [
      0.0
    ]
  },
  "target_mean": {
    "steps": [
      800
    ],
    "timestamps": [
      "2023-07-05T15:52:45.536106"
    ],
    "values": [
      0.1357041295369466
    ]
  },
  "td_error_abs": {
    "steps": [
      800
    ],
    "timestamps": [
      "2023-07-05T15:52:45.535913"
    ],
    "values": [
      0.779019775390625
    ]
  },
  "test_ep_length_mean": {
    "steps": [
      25
    ],
    "timestamps": [
      "2023-07-05T15:52:44.174171"
    ],
    "values": [
      25.0
    ]
  },
  "test_return_mean": {
    "steps": [
      25
    ],
    "timestamps": [
      "2023-07-05T15:52:44.173870"
    ],
    "values": [
      -900.631135275224
    ]
  },
  "test_return_std": {
    "steps": [
      25
    ],
    "timestamps": [
      "2023-07-05T15:52:44.174123"
    ],
    "values": [
      164.4283411177801
    ]
  }
}