{
  "ep_length_mean": [
    25.0
  ],
  "ep_length_mean_T": [
    25
  ],
  "epsilon": [
    1.0
  ],
  "epsilon_T": [
    25
  ],
  "return_mean": [
    {
      "dtype": "float64",
      "py/object": "numpy.float64",
      "value": -625.5321855986016
    }
  ],
  "return_mean_T": [
    25
  ],
  "return_std": [
    {
      "dtype": "float64",
      "py/object": "numpy.float64",
      "value": 0.0
    }
  ],
  "return_std_T": [
    25
  ],
  "test_ep_length_mean": [
    25.0
  ],
  "test_ep_length_mean_T": [
    25
  ],
  "test_return_mean": [
    {
      "dtype": "float64",
      "py/object": "numpy.float64",
      "value": -688.5843565627746
    }
  ],
  "test_return_mean_T": [
    25
  ],
  "test_return_std": [
    {
      "dtype": "float64",
      "py/object": "numpy.float64",
      "value": 177.72653389664504
    }
  ],
  "test_return_std_T": [
    25
  ]
}